zen_lib/__init__.py
zen_lib/microdot.py
zen_lib/zen_esp.py
zen_lib/zen_gui.py
zen_lib/zen_thread_pool.py
zen_lib/zen_tool.py
zen_lib-0.2.1.dist-info/License.txt
zen_lib-0.2.1.dist-info/METADATA
zen_lib-0.2.1.dist-info/WHEEL
zen_lib-0.2.1.dist-info/top_level.txt
zen_lib-0.2.1.dist-info/RECORD
