Metadata-Version: 2.1
Name: zen_lib
Version: 0.2.1
Summary: personal utilities code for esp32
Author: lhyweb
Author-email: lhyweb@gmail.com
Classifier: Programming Language :: Python :: 3
Classifier: License :: OSI Approved :: MIT License
Classifier: Operating System :: OS Independent
License-File: License.txt
